MANIFEST.in
README.md
setup.cfg
setup.py
higlass_jupyter/__init__.py
higlass_jupyter/_version.py
higlass_jupyter.egg-info/PKG-INFO
higlass_jupyter.egg-info/SOURCES.txt
higlass_jupyter.egg-info/dependency_links.txt
higlass_jupyter.egg-info/not-zip-safe
higlass_jupyter.egg-info/requires.txt
higlass_jupyter.egg-info/top_level.txt
higlass_jupyter/static/extension.js
higlass_jupyter/static/index.js
higlass_jupyter/static/index.js.map